maze_dataset/__init__.py
maze_dataset/constants.py
maze_dataset/py.typed
maze_dataset/testing_utils.py
maze_dataset/token_utils.py
maze_dataset/utils.py
maze_dataset/benchmark/__init__.py
maze_dataset/benchmark/config_sweep.py
maze_dataset/benchmark/speed.py
maze_dataset/benchmark/sweep_fit.py
maze_dataset/dataset/__init__.py
maze_dataset/dataset/collected_dataset.py
maze_dataset/dataset/configs.py
maze_dataset/dataset/dataset.py
maze_dataset/dataset/filters.py
maze_dataset/dataset/maze_dataset.py
maze_dataset/dataset/maze_dataset_config.py
maze_dataset/dataset/rasterized.py
maze_dataset/dataset/success_predict_math.py
maze_dataset/generation/__init__.py
maze_dataset/generation/default_generators.py
maze_dataset/generation/generators.py
maze_dataset/generation/registration.py
maze_dataset/generation/seed.py
maze_dataset/maze/__init__.py
maze_dataset/maze/lattice_maze.py
maze_dataset/plotting/__init__.py
maze_dataset/plotting/plot_dataset.py
maze_dataset/plotting/plot_maze.py
maze_dataset/plotting/plot_svg_fancy.py
maze_dataset/plotting/plot_tokens.py
maze_dataset/plotting/print_tokens.py
maze_dataset/tokenization/__init__.py
maze_dataset/tokenization/common.py
maze_dataset/tokenization/maze_tokenizer.py
maze_dataset/tokenization/maze_tokenizer_legacy.py
maze_dataset/tokenization/modular/MazeTokenizerModular_tested.fst
maze_dataset/tokenization/modular/__init__.py
maze_dataset/tokenization/modular/all_instances.py
maze_dataset/tokenization/modular/all_tokenizers.py
maze_dataset/tokenization/modular/element_base.py
maze_dataset/tokenization/modular/elements.py
maze_dataset/tokenization/modular/fst.py
maze_dataset/tokenization/modular/fst_load.py
maze_dataset/tokenization/modular/hashing.py
maze_dataset/tokenization/modular/maze_tokenizer_modular.py
maze_dataset/tokenization/modular/save_hashes.py
maze_dataset-1.4.2.dist-info/METADATA
maze_dataset-1.4.2.dist-info/WHEEL
maze_dataset-1.4.2.dist-info/licenses/LICENSE.md
maze_dataset-1.4.2.dist-info/RECORD
