Metadata-Version: 2.4
Name: maze-dataset
Version: 1.4.2
Summary: generating and working with datasets of mazes
Project-URL: Homepage, https://github.com/understanding-search/maze-dataset
Project-URL: Documentation, https://understanding-search.github.io/maze-dataset/
Project-URL: Repository, https://github.com/understanding-search/maze-dataset
Project-URL: Issues, https://github.com/understanding-search/maze-dataset/issues
Author-email: Michael Ivanitskiy <mivanits@umich.edu>, Aaron Sandoval <aaron.sandoval10@gmail.com>, Rusheb Shah <rusheb.shah@gmail.com>, Dan Valentine <danvalentine256@gmail.com>, Lucia Quirke <luciaq@canva.com>, Can Rager <can.rager@posteo.de>, Alex Spies <alexfspies@gmail.com>, Chris Mathwin <cwmathwin@gmail.com>, Tilman Rauker <traeuker@googlemail.com>, Guillaume Corlouer <guillaume.corlouer@gmail.com>
License-File: LICENSE.md
Keywords: dataset,labyrinth,maze,mazes,pathfinding,procedural,tokenization
Requires-Python: >=3.10
Requires-Dist: ipykernel>=6.22.0
Requires-Dist: jaxtyping>=0.2.19
Requires-Dist: jupyter>=1.0.0
Requires-Dist: matplotlib>=3.7.0
Requires-Dist: muutils>=0.8.3
Requires-Dist: numpy
Requires-Dist: tqdm>=4.65.0
Requires-Dist: zanj>=0.5.0
Provides-Extra: tokenization
Requires-Dist: frozendict>=2.4.4; extra == 'tokenization'
Requires-Dist: rust-fst>=0.1.2; (platform_system != 'Darwin') and extra == 'tokenization'
